spl2_testing_framework/__init__.py
spl2_testing_framework/conftest.py
spl2_testing_framework/launch_remotely_spl2.py
spl2_testing_framework/logger_manager.py
spl2_testing_framework/pytest.ini.sample
spl2_testing_framework/single_spl2_file_runner.py
spl2_testing_framework/spl2_test_config.json
spl2_testing_framework/spl2_utils/assertions.spl2
spl2_testing_framework/spl2_utils/logs_to_metrics.spl2
spl2_testing_framework/test_runner.py
spl2_testing_framework/tools/__init__.py
spl2_testing_framework/tools/create_diff_sheet.py
spl2_testing_framework/tools/jobs/__init__.py
spl2_testing_framework/tools/jobs/cli_job.py
spl2_testing_framework/tools/jobs/cloud_job.py
spl2_testing_framework/tools/jobs/job.py
spl2_testing_framework/tools/jobs/splunk_job.py
spl2_testing_framework/tools/jobs/test_cloud_job.py
spl2_testing_framework/tools/performance.py
spl2_testing_framework/tools/results.py
spl2_testing_framework/tools/search_clients/__init__.py
spl2_testing_framework/tools/search_clients/cli_search_client.py
spl2_testing_framework/tools/search_clients/cloud_search_client.py
spl2_testing_framework/tools/search_clients/search_client.py
spl2_testing_framework/tools/search_clients/splunk_search_client.py
spl2_testing_framework/tools/spl2test_runner.py
spl2_testing_framework/tools/test_discovery.py
spl2_testing_framework/tools/test_types.py
spl2_testing_framework/tools/utils.py
spl2_testing_framework-1.5.0.dist-info/LICENSE
spl2_testing_framework-1.5.0.dist-info/METADATA
spl2_testing_framework-1.5.0.dist-info/WHEEL
spl2_testing_framework-1.5.0.dist-info/entry_points.txt
spl2_testing_framework-1.5.0.dist-info/RECORD
