Metadata-Version: 2.1
Name: spl2-testing-framework
Version: 1.5.0
Summary: SPL2 Testing Framework
Home-page: https://github.com/splunk/spl2-testing-framework
Keywords: SPL2 testing framework
Author: mgazda-splunk
Author-email: mgazda@splunk.com
Requires-Python: >=3.7.1,<4.0.0
Classifier: Programming Language :: Python :: 3
Classifier: Programming Language :: Python :: 3.8
Classifier: Programming Language :: Python :: 3.9
Classifier: Programming Language :: Python :: 3.10
Classifier: Programming Language :: Python :: 3.11
Requires-Dist: numpy (>=1.21,<1.22) ; python_version < "3.8"
Requires-Dist: numpy (>=1.21,<1.24) ; python_version >= "3.8" and python_version < "3.10"
Requires-Dist: numpy (>=1.25,<2.0) ; python_version >= "3.10" and python_version < "3.13"
Requires-Dist: numpy (>=1.26,<2.0) ; python_version >= "3.13"
Requires-Dist: openpyxl (>=3.1.2,<4.0.0)
Requires-Dist: pandas (==1.3.5) ; python_version < "3.8"
Requires-Dist: pandas (==1.5.3) ; python_version >= "3.8" and python_version < "3.10"
Requires-Dist: pandas (>=2.0.3,<3.0.0) ; python_version >= "3.10" and python_version < "3.13"
Requires-Dist: pandas (>=2.1.0,<3.0.0) ; python_version >= "3.13"
Requires-Dist: pytest (==7.4.4)
Requires-Dist: pytest-subtests (==0.13.1)
Requires-Dist: pytest-xdist (==3.5.0)
Requires-Dist: requests (>=2.31.0,<3.0.0)
Requires-Dist: tabulate (==0.9.0)
Requires-Dist: urllib3 (>=1.26.19,<2.0.0)
Project-URL: Repository, https://github.com/splunk/spl2-testing-framework
